tekleo_common_utils/__init__.py
tekleo_common_utils/utils_class.py
tekleo_common_utils/utils_config.py
tekleo_common_utils/utils_cryptography.py
tekleo_common_utils/utils_env.py
tekleo_common_utils/utils_file.py
tekleo_common_utils/utils_id.py
tekleo_common_utils/utils_image.py
tekleo_common_utils/utils_math.py
tekleo_common_utils/utils_method.py
tekleo_common_utils/utils_opencv.py
tekleo_common_utils/utils_pdf.py
tekleo_common_utils/utils_ping.py
tekleo_common_utils/utils_random.py
tekleo_common_utils/utils_string.py
tekleo_common_utils/utils_time.py
tekleo_common_utils-0.0.2.8.dist-info/LICENSE.txt
tekleo_common_utils-0.0.2.8.dist-info/METADATA
tekleo_common_utils-0.0.2.8.dist-info/WHEEL
tekleo_common_utils-0.0.2.8.dist-info/top_level.txt
tekleo_common_utils-0.0.2.8.dist-info/RECORD
