Metadata-Version: 2.1
Name: tekleo-common-utils
Version: 0.0.2.8
Summary: UNKNOWN
Home-page: https://github.com/jpleorx/tekleo-common-utils
Author: Leo Ertuna
Author-email: leo.ertuna@gmail.com
License: Creative Commons Attribution-NonCommercial-NoDerivatives 4.0 International Public License
Download-URL: https://pypi.org/project/tekleo-common-utils/
Platform: UNKNOWN
License-File: LICENSE.txt
Requires-Dist: pytz
Requires-Dist: tzlocal
Requires-Dist: injectable
Requires-Dist: requests
Requires-Dist: user-agent
Requires-Dist: Faker
Requires-Dist: namesgenerator
Requires-Dist: Pillow
Requires-Dist: numpy
Requires-Dist: opencv-python
Requires-Dist: pillow-heif
Requires-Dist: pdf2image
Requires-Dist: PyPDF2
Requires-Dist: pdfminer
Requires-Dist: tekleo-common-message-protocol
